<?xml version="1.0" encoding="UTF-8"?>
<ContextState>
<org.eclipse.mylyn.context.ui.editors>
<MonitoredWindowOpenEditors class="org.eclipse.ui.internal.WorkbenchWindow" isActive="true" isLaunching="true" number="0">
<editor id="org.eclipse.jdt.ui.CompilationUnitEditor">
<input factoryID="org.eclipse.ui.part.FileEditorInputFactory" path="/IFM11/src/ifm11/utils/Methods.java"/>
<editorState selectionHorizontalPixel="0" selectionLength="0" selectionOffset="3841" selectionTopPixel="2340"/>
</editor>
<editor id="org.eclipse.jdt.ui.CompilationUnitEditor">
<input factoryID="org.eclipse.ui.part.FileEditorInputFactory" path="/IFM11/src/ifm11/utils/DBUtils.java"/>
<editorState selectionHorizontalPixel="0" selectionLength="0" selectionOffset="144409" selectionTopPixel="154934"/>
</editor>
<editor id="org.eclipse.jdt.ui.CompilationUnitEditor">
<input factoryID="org.eclipse.ui.part.FileEditorInputFactory" path="/IFM11/src/ifm11/utils/CONS.java"/>
<editorState selectionHorizontalPixel="0" selectionLength="130" selectionOffset="7793" selectionTopPixel="7618"/>
</editor>
<editor id="org.eclipse.jdt.ui.CompilationUnitEditor">
<input factoryID="org.eclipse.ui.part.FileEditorInputFactory" path="/IFM11/src/ifm11/main/MainActv.java"/>
<editorState selectionHorizontalPixel="0" selectionLength="0" selectionOffset="16500" selectionTopPixel="17862"/>
</editor>
</MonitoredWindowOpenEditors>
</org.eclipse.mylyn.context.ui.editors>
</ContextState>